pyqiniu_util/__init__.py
pyqiniu_util/qiniu_util.py
pyqiniu_util-1.0.1.dist-info/LICENSE
pyqiniu_util-1.0.1.dist-info/METADATA
pyqiniu_util-1.0.1.dist-info/WHEEL
pyqiniu_util-1.0.1.dist-info/top_level.txt
pyqiniu_util-1.0.1.dist-info/zip-safe
pyqiniu_util-1.0.1.dist-info/RECORD
