Metadata-Version: 2.1
Name: pyqiniu_util
Version: 1.0.1
Summary: 七牛云助手
Home-page: https://github.com/buyfakett
Author: buyfakett
Author-email: buyfakett@vip.qq.com
License: MIT
Requires-Python: >=3.6
License-File: LICENSE
Requires-Dist: qiniu
Requires-Dist: pyyaml-util
